Workbook
Name _DLX1: #REF!
Name _DLX2.INC: HAVER_data!$A$1:$W$9
Name _DLX3.INC: #REF!
Name BoxPlot: "BoxPlot"
Name Bubble: "Bubble"
Name Candlestick: "Candlestick"
Name Chart: "Chart"
Name ChartImage: "ChartImage"
Name ColumnRange: "ColumnRange"
Name Dumbbell: "Dumbbell"
Name Heatmap: "Heatmap"
Name Histogram: "Histogram"
Name Map: "Map"
Name OHLC: "OHLC"
Name PieChart: "PieChart"
Name Scatter: "Scatter"
Name Series: "Series"
Name Stripe: "Stripe"
Name Table: "Table"
Name TreeMap: "TreeMap"
Name Waterfall: "Waterfall"

Sheet HAVER_data
A1: 1998-Jan !M | B1: ffedtar@usecon | C1: CINF1@USECON | D1: CINF5@USECON | E1: LR@USECON | F1: MLU6@USECON | G1: FM2@USECON | H1: LH@USECON | I1: PCU@USECON | J1: PCUSLFE@USECON | K1: JCBM@USECON | L1: JCXFEBM@USECON | M1: USPHPIM@USECON | N1: GSACPPIc@USECON | O1: pzraw@USECON | P1: LANAGRD@USECON | Q1: LKPRIVA@USECON | R1: LEPRIVA@USECON | S1: FYTNCAA@USECON | T1: FYTNCAB@USECON | U1: FYTNCAD@USECON | V1: FYTNCAT@USECON | W1: MGDPN@USECON
A2: .DESC | B2: Federal Open Market Committee: Fed Funds Target Rate (%) | C2: University of Michigan: Expected Inflation Rate, Next Year (%) | D2: University of Michigan: Expected Inflation Rate, Next 5 Years (%) | E2: Civilian Unemployment Rate: 16 yr + (SA, %) | F2: Unempl+Margin Attach+Part Time Econ Reasons/CLF + Margin Attach (SA,%) | G2: Money Stock: M2 (SA, Bil.$) | H2: Not in the Labor Force: 16 yr + (SA, Thous) | I2: CPI-U: All Items (SA, 1982-84=100) | J2: CPI-U: All Items Less Food and Energy (SA, 1982-84=100) | K2: PCE: Chain Price Index (SA, 2017=100) | L2: PCE less Food & Energy: Chain Price Index (SA, 2017=100) | M2: FHFA House Price Index: Purchase Only, United States (SA, Jan-91=100) | N2: Green Street Commercial Property Price Index: Core Sector (NSA, Aug-07=100) | O2: CRB Spot Commodity Price Index: Raw Industrials (1967=100) | P2: Change in Total Nonfarm Employment (SA, Thous) | Q2: Avg Weekly Earnings: Prod & Nonsupervisory: Total Private Industries(SA, $/Week) | R2: Avg Hourly Earnings: Prod & Nonsupervisory: Total Private Industries(SA, $/Hour) | S2: Treasury Nominal Coupon Spot Yield: 6 Months (AVG, %) | T2: Treasury Nominal Coupon Spot Yield: 1 Year (AVG, %) | U2: Treasury Nominal Coupon Spot Yield: 2 Years (AVG, %) | V2: Treasury Nominal Coupon Spot Yield: 10 Years (AVG, %) | W2: S&P Global's Monthly GDP (SAAR, Bil.$)
A3: .T1 | B3: Oct-1982 | C3: Jan-1978 | D3: Feb-1979 | E3: Jan-1948 | F3: Jan-1994 | G3: Jan-1959 | H3: Jan-1948 | I3: Jan-1947 | J3: Jan-1957 | K3: Jan-1959 | L3: Jan-1959 | M3: Jan-1991 | N3: Dec-1997 | O3: Jul-1946 | P3: Feb-1939 | Q3: Jan-1964 | R3: Jan-1964 | S3: Jan-1976 | T3: Jan-1976 | U3: Jan-1976 | V3: Jan-1976 | W3: Jan-1992
A4: .TN | B4: Jun-2025 | C4: Jun-2025 | D4: Jun-2025 | E4: Jun-2025 | F4: Jun-2025 | G4: May-2025 | H4: Jun-2025 | I4: May-2025 | J4: May-2025 | K4: May-2025 | L4: May-2025 | M4: Apr-2025 | N4: Jun-2025 | O4: Jun-2025 | P4: Jun-2025 | Q4: Jun-2025 | R4: Jun-2025 | S4: May-2025 | T4: May-2025 | U4: May-2025 | V4: May-2025 | W4: May-2025
A5: .DTLM | B5: Jul-01-2025 02:25 | C5: Jun-27-2025 22:00 | D5: Jun-27-2025 22:00 | E5: Jul-03-2025 20:32 | F5: Jul-03-2025 20:31 | G5: Jun-25-2025 01:03 | H5: Jul-03-2025 20:32 | I5: Jun-11-2025 20:30 | J5: Jun-11-2025 20:30 | K5: Jun-27-2025 20:31 | L5: Jun-27-2025 20:31 | M5: Jun-24-2025 21:01 | N5: Jul-07-2025 23:10 | O5: Jul-01-2025 09:32 | P5: Jul-03-2025 20:30 | Q5: Jul-03-2025 20:30 | R5: Jul-03-2025 20:30 | S5: Jun-12-2025 22:41 | T5: Jun-12-2025 22:41 | U5: Jun-12-2025 22:41 | V5: Jun-12-2025 22:41 | W5: Jul-02-2025 03:05
A6: .DATA_TYPE | B6: % | C6: % | D6: % | E6: % | F6: % | G6: US$ | H6: Units | I6: INDEX | J6: INDEX | K6: INDEX | L6: INDEX | M6: INDEX | N6: INDEX | O6: INDEX | P6: Units | Q6: US$ | R6: US$ | S6: % | T6: % | U6: % | V6: % | W6: US$
A7: .GRP | B7: F04 | C7: C30 | D7: C30 | E7: E02 | F7: E02 | G7: M01 | H7: E02 | I7: P01 | J7: P01 | K7: N09 | L7: N09 | M7: H63 | N7: H93 | O7: P50 | P7: E30 | Q7: E30 | R7: E30 | S7: F57 | T7: F57 | U7: F57 | V7: F57 | W7: N28
A8: .GRPDESC | B8: Fed Funds Target Rate | C8: University of Michigan Consumer Sentiment Index | D8: University of Michigan Consumer Sentiment Index | E8: Household Survey Press Release, SA | F8: Household Survey Press Release, SA | G8: Money Stock [FRB H.6] | H8: Household Survey Press Release, SA | I8: Consumer Price Index Press Release, SA & NSA | J8: Consumer Price Index Press Release, SA & NSA | K8: Personal Income & Outlays Press Release, Monthly | L8: Personal Income & Outlays Press Release, Monthly | M8: FHFA National House Price Index, Monthly | N8: Green Street Advisors Commercial Property Price Index | O8: CRB Commodity Spot & Futures Price Indexes | P8: Establishment Survey Press Release SA | Q8: Establishment Survey Press Release SA | R8: Establishment Survey Press Release SA | S8: Treasury Yield Curve [Treasury] | T8: Treasury Yield Curve [Treasury] | U8: Treasury Yield Curve [Treasury] | V8: Treasury Yield Curve [Treasury] | W8: MA Monthly GDP Index
A9: .GEO | B9: 111 | C9: 111 | D9: 111 | E9: 111 | F9: 111 | G9: 111 | H9: 111 | I9: 111 | J9: 111 | K9: 111 | L9: 111 | M9: 111 | N9: 111 | O9: 111 | P9: 111 | Q9: 111 | R9: 111 | S9: 111 | T9: 111 | U9: 111 | V9: 111 | W9: 111
A10: 1998-Jan | B10: 5.5 | C10: 2.3 | D10: 2.9 | E10: 4.6 | F10: 8.4 | G10: 4056.2 | H10: 67143 | I10: 162 | J10: 171.6 | K10: 70.736 | L10: 72.21 | M10: 120.95 | N10: 48.57 | O10: 299.61 | P10: 257 | Q10: 442.53 | R10: 12.79 | S10: 5.38 | T10: 5.38 | U10: 5.38 | V10: 5.66 | W10: 8770.136
A11: 1998-Feb | B11: 5.5 | C11: 2.4 | D11: 2.9 | E11: 4.6 | F11: 8.3 | G11: 4088.9 | H11: 67288 | I11: 162 | J11: 171.9 | K11: 70.699 | L11: 72.272 | M11: 121.82 | N11: 49.08 | O11: 297.29 | P11: 211 | Q11: 442.64 | R11: 12.83 | S11: 5.41 | T11: 5.42 | U11: 5.44 | V11: 5.73 | W11: 8896.288
A12: 1998-Mar | B12: 5.5 | C12: 2.5 | D12: 2.8 | E12: 4.7 | F12: 8.4 | G12: 4114.3 | H12: 67311 | I12: 162 | J12: 172.2 | K12: 70.71 | L12: 72.349 | M12: 122.2 | N12: 51.5 | O12: 302.89 | P12: 148 | Q12: 442.73 | R12: 12.87 | S12: 5.47 | T12: 5.52 | U12: 5.59 | V12: 5.83 | W12: 8933.015
A13: 1998-Apr | B13: 5.5 | C13: 2.4 | D13: 2.7 | E13: 4.3 | F13: 8 | G13: 4140.2 | H13: 67581 | I13: 162.2 | J13: 172.5 | K13: 70.798 | L13: 72.482 | M13: 122.73 | N13: 51.5 | O13: 301.25 | P13: 281 | Q13: 444.45 | R13: 12.92 | S13: 5.45 | T13: 5.51 | U13: 5.59 | V13: 5.81 | W13: 8926.116
A14: 1998-May | B14: 5.5 | C14: 2.6 | D14: 2.8 | E14: 4.4 | F14: 8 | G14: 4164.4 | H14: 67527 | I14: 162.6 | J14: 172.9 | K14: 70.895 | L14: 72.552 | M14: 123.23 | N14: 52.09 | O14: 305.4 | P14: 400 | Q14: 447.47 | R14: 12.97 | S14: 5.48 | T14: 5.54 | U14: 5.62 | V14: 5.83 | W14: 8953.519
A15: 1998-Jun | B15: 5.5 | C15: 2.7 | D15: 2.9 | E15: 4.5 | F15: 8.1 | G15: 4184.1 | H15: 67630 | I15: 162.8 | J15: 173.2 | K15: 70.835 | L15: 72.461 | M15: 124 | N15: 52.37 | O15: 299.72 | P15: 230 | Q15: 446.86 | R15: 12.99 | S15: 5.47 | T15: 5.51 | U15: 5.56 | V15: 5.65 | W15: 9029.462
A16: 1998-Jul | B16: 5.5 | C16: 2.6 | D16: 2.7 | E16: 4.5 | F16: 8.2 | G16: 4203.8 | H16: 67682 | I16: 163.2 | J16: 173.5 | K16: 71.01 | L16: 72.665 | M16: 124.35 | N16: 52.28 | O16: 295.56 | P16: 135 | Q16: 448.5 | R16: 13 | S16: 5.41 | T16: 5.45 | U16: 5.5 | V16: 5.62 | W16: 9050.779
A17: 1998-Aug | B17: 5.5 | C17: 2.4 | D17: 2.7 | E17: 4.5 | F17: 7.9 | G17: 4228.7 | H17: 67910 | I17: 163.4 | J17: 174 | K17: 71.108 | L17: 72.807 | M17: 124.87 | N17: 52.88 | O17: 290.17 | P17: 335 | Q17: 450.92 | R17: 13.07 | S17: 5.3 | T17: 5.31 | U17: 5.32 | V17: 5.47 | W17: 9099.745
A18: 1998-Sep | B18: 5.4833 | C18: 2.3 | D18: 2.9 | E18: 4.6 | F18: 8 | G18: 4267.7 | H18: 67413 | I18: 163.5 | J18: 174.2 | K18: 71.067 | L18: 72.795 | M18: 125.68 | N18: 51 | O18: 280.98 | P18: 198 | Q18: 449.67 | R18: 13.11 | S18: 4.96 | T18: 4.88 | U18: 4.77 | V18: 4.91 | W18: 9212.767
A19: 1998-Oct | B19: 5.1129 | C19: 2.5 | D19: 2.8 | E19: 4.5 | F19: 7.9 | G19: 4307.9 | H19: 67640 | I19: 163.9 | J19: 174.4 | K19: 71.223 | L19: 72.937 | M19: 126.2 | N19: 50.99 | O19: 275.73 | P19: 204 | Q19: 453.33 | R19: 13.14 | S19: 4.42 | T19: 4.35 | U19: 4.27 | V19: 4.67 | W19: 9264.281
A20: 1998-Nov | B20: 4.8833 | C20: 2.3 | D20: 2.8 | E20: 4.4 | F20: 7.7 | G20: 4346.6 | H20: 67723 | I20: 164.1 | J20: 174.8 | K20: 71.226 | L20: 72.95 | M20: 127.04 | N20: 51.59 | O20: 268.88 | P20: 275 | Q20: 453.05 | R20: 13.17 | S20: 4.68 | T20: 4.68 | U20: 4.69 | V20: 4.99 | W20: 9306.272
A21: 1998-Dec | B21: 4.75 | C21: 2.5 | D21: 2.9 | E21: 4.4 | F21: 7.6 | G21: 4375.6 | H21: 67635 | I21: 164.4 | J21: 175.4 | K21: 71.298 | L21: 73.076 | M21: 127.61 | N21: 51.63 | O21: 265.94 | P21: 372 | Q21: 455.75 | R21: 13.21 | S21: 4.67 | T21: 4.64 | U21: 4.6 | V21: 4.8 | W21: 9311.42
... A337: 2025-Apr | B337: 4.375 | C337: 6.5 | D337: 4.4 | E337: 4.2 | F337: 7.8 | G337: 21862.4 | H337: 102062 | I337: 320.321 | J337: 326.43 | K337: 125.939 | L337: 125.288 | M337: 434.93 | N337: 127.85 | O337: 560.83 | P337: 158 | Q337: 1046.39 | R337: 31.05 | S337: 4.13 | T337: 3.99 | U337: 3.81 | V337: 4.31 | W337: 30248.402
A338: 2025-May | B338: 4.375 | C338: 6.6 | D338: 4.2 | E338: 4.2 | F338: 7.8 | G338: 21942 | H338: 102875 | I338: 320.58 | J338: 326.854 | K338: 126.11 | L338: 125.512 | N338: 128.25 | O338: 561.29 | P338: 144 | Q338: 1049.76 | R338: 31.15 | S338: 4.24 | T338: 4.11 | U338: 3.94 | V338: 4.49 | W338: 30064.463
A339: 2025-Jun | B339: 4.375 | C339: 5 | D339: 4 | E339: 4.1 | F339: 7.7 | H339: 103204 | N339: 128.25 | O339: 565.43 | P339: 147 | Q339: 1046.54 | R339: 31.24

Sheet data
A1: Date | B1: FF | C1: CINF1 | D1: CINF5 | E1: MLU6 | F1: FM2 | G1: LH | H1: PCU | I1: PCUSLFE | J1: JCBM | K1: JCXFEBM | L1: USPHPIM | M1: GSACPPIC | N1: PZRAW | O1: LANAGRD | P1: LKPRIVA | Q1: LEPRIVA | R1: Yield6m | S1: Yield1Y | T1: Yield2Y | U1: Yield10Y | V1: MGDPN
A2: 35796 | B2: =HAVER_data!B10 -> 5.5 | C2: =HAVER_data!C10 -> 2.3 | D2: =HAVER_data!D10 -> 2.9 | E2: =HAVER_data!F10 -> 8.4 | F2: =HAVER_data!G10 -> 4056.2 | G2: =HAVER_data!H10 -> 67143 | H2: =HAVER_data!I10 -> 162 | I2: =HAVER_data!J10 -> 171.6 | J2: =HAVER_data!K10 -> 70.736 | K2: =HAVER_data!L10 -> 72.21 | L2: =HAVER_data!M10 -> 120.95 | ... V2: =HAVER_data!W10 -> 8770.136
A3: 35827 | B3: =HAVER_data!B11 -> 5.5 | C3: =HAVER_data!C11 -> 2.4 | D3: =HAVER_data!D11 -> 2.9 | E3: =HAVER_data!F11 -> 8.3 | F3: =HAVER_data!G11 -> 4088.9 | G3: =HAVER_data!H11 -> 67288 | H3: =HAVER_data!I11 -> 162 | I3: =HAVER_data!J11 -> 171.9 | J3: =HAVER_data!K11 -> 70.699 | K3: =HAVER_data!L11 -> 72.272 | L3: =HAVER_data!M11 -> 121.82 | ... V3: =HAVER_data!W11 -> 8896.288
A4: 35855 | B4: =HAVER_data!B12 -> 5.5 | C4: =HAVER_data!C12 -> 2.5 | D4: =HAVER_data!D12 -> 2.8 | E4: =HAVER_data!F12 -> 8.4 | F4: =HAVER_data!G12 -> 4114.3 | G4: =HAVER_data!H12 -> 67311 | H4: =HAVER_data!I12 -> 162 | I4: =HAVER_data!J12 -> 172.2 | J4: =HAVER_data!K12 -> 70.71 | K4: =HAVER_data!L12 -> 72.349 | L4: =HAVER_data!M12 -> 122.2 | ... V4: =HAVER_data!W12 -> 8933.015
A5: 35886 | B5: =HAVER_data!B13 -> 5.5 | C5: =HAVER_data!C13 -> 2.4 | D5: =HAVER_data!D13 -> 2.7 | E5: =HAVER_data!F13 -> 8 | F5: =HAVER_data!G13 -> 4140.2 | G5: =HAVER_data!H13 -> 67581 | H5: =HAVER_data!I13 -> 162.2 | I5: =HAVER_data!J13 -> 172.5 | J5: =HAVER_data!K13 -> 70.798 | K5: =HAVER_data!L13 -> 72.482 | L5: =HAVER_data!M13 -> 122.73 | ... V5: =HAVER_data!W13 -> 8926.116
A6: 35916 | B6: =HAVER_data!B14 -> 5.5 | C6: =HAVER_data!C14 -> 2.6 | D6: =HAVER_data!D14 -> 2.8 | E6: =HAVER_data!F14 -> 8 | F6: =HAVER_data!G14 -> 4164.4 | G6: =HAVER_data!H14 -> 67527 | H6: =HAVER_data!I14 -> 162.6 | I6: =HAVER_data!J14 -> 172.9 | J6: =HAVER_data!K14 -> 70.895 | K6: =HAVER_data!L14 -> 72.552 | L6: =HAVER_data!M14 -> 123.23 | ... V6: =HAVER_data!W14 -> 8953.519
A7: 35947 | B7: =HAVER_data!B15 -> 5.5 | C7: =HAVER_data!C15 -> 2.7 | D7: =HAVER_data!D15 -> 2.9 | E7: =HAVER_data!F15 -> 8.1 | F7: =HAVER_data!G15 -> 4184.1 | G7: =HAVER_data!H15 -> 67630 | H7: =HAVER_data!I15 -> 162.8 | I7: =HAVER_data!J15 -> 173.2 | J7: =HAVER_data!K15 -> 70.835 | K7: =HAVER_data!L15 -> 72.461 | L7: =HAVER_data!M15 -> 124 | ... V7: =HAVER_data!W15 -> 9029.462
A8: 35977 | B8: =HAVER_data!B16 -> 5.5 | C8: =HAVER_data!C16 -> 2.6 | D8: =HAVER_data!D16 -> 2.7 | E8: =HAVER_data!F16 -> 8.2 | F8: =HAVER_data!G16 -> 4203.8 | G8: =HAVER_data!H16 -> 67682 | H8: =HAVER_data!I16 -> 163.2 | I8: =HAVER_data!J16 -> 173.5 | J8: =HAVER_data!K16 -> 71.01 | K8: =HAVER_data!L16 -> 72.665 | L8: =HAVER_data!M16 -> 124.35 | ... V8: =HAVER_data!W16 -> 9050.779
A9: 36008 | B9: =HAVER_data!B17 -> 5.5 | C9: =HAVER_data!C17 -> 2.4 | D9: =HAVER_data!D17 -> 2.7 | E9: =HAVER_data!F17 -> 7.9 | F9: =HAVER_data!G17 -> 4228.7 | G9: =HAVER_data!H17 -> 67910 | H9: =HAVER_data!I17 -> 163.4 | I9: =HAVER_data!J17 -> 174 | J9: =HAVER_data!K17 -> 71.108 | K9: =HAVER_data!L17 -> 72.807 | L9: =HAVER_data!M17 -> 124.87 | ... V9: =HAVER_data!W17 -> 9099.745
A10: 36039 | B10: =HAVER_data!B18 -> 5.4833 | C10: =HAVER_data!C18 -> 2.3 | D10: =HAVER_data!D18 -> 2.9 | E10: =HAVER_data!F18 -> 8 | F10: =HAVER_data!G18 -> 4267.7 | G10: =HAVER_data!H18 -> 67413 | H10: =HAVER_data!I18 -> 163.5 | I10: =HAVER_data!J18 -> 174.2 | J10: =HAVER_data!K18 -> 71.067 | K10: =HAVER_data!L18 -> 72.795 | L10: =HAVER_data!M18 -> 125.68 | ... V10: =HAVER_data!W18 -> 9212.767
A11: 36069 | B11: =HAVER_data!B19 -> 5.1129 | C11: =HAVER_data!C19 -> 2.5 | D11: =HAVER_data!D19 -> 2.8 | E11: =HAVER_data!F19 -> 7.9 | F11: =HAVER_data!G19 -> 4307.9 | G11: =HAVER_data!H19 -> 67640 | H11: =HAVER_data!I19 -> 163.9 | I11: =HAVER_data!J19 -> 174.4 | J11: =HAVER_data!K19 -> 71.223 | K11: =HAVER_data!L19 -> 72.937 | L11: =HAVER_data!M19 -> 126.2 | ... V11: =HAVER_data!W19 -> 9264.281
A12: 36100 | B12: =HAVER_data!B20 -> 4.8833 | C12: =HAVER_data!C20 -> 2.3 | D12: =HAVER_data!D20 -> 2.8 | E12: =HAVER_data!F20 -> 7.7 | F12: =HAVER_data!G20 -> 4346.6 | G12: =HAVER_data!H20 -> 67723 | H12: =HAVER_data!I20 -> 164.1 | I12: =HAVER_data!J20 -> 174.8 | J12: =HAVER_data!K20 -> 71.226 | K12: =HAVER_data!L20 -> 72.95 | L12: =HAVER_data!M20 -> 127.04 | ... V12: =HAVER_data!W20 -> 9306.272
A13: 36130 | B13: =HAVER_data!B21 -> 4.75 | C13: =HAVER_data!C21 -> 2.5 | D13: =HAVER_data!D21 -> 2.9 | E13: =HAVER_data!F21 -> 7.6 | F13: =HAVER_data!G21 -> 4375.6 | G13: =HAVER_data!H21 -> 67635 | H13: =HAVER_data!I21 -> 164.4 | I13: =HAVER_data!J21 -> 175.4 | J13: =HAVER_data!K21 -> 71.298 | K13: =HAVER_data!L21 -> 73.076 | L13: =HAVER_data!M21 -> 127.61 | ... V13: =HAVER_data!W21 -> 9311.42
... A329: 45748 | B329: =HAVER_data!B337 -> 4.375 | C329: =HAVER_data!C337 -> 6.5 | D329: =HAVER_data!D337 -> 4.4 | E329: =HAVER_data!F337 -> 7.8 | F329: =HAVER_data!G337 -> 21862.4 | G329: =HAVER_data!H337 -> 102062 | H329: =HAVER_data!I337 -> 320.321 | I329: =HAVER_data!J337 -> 326.43 | J329: =HAVER_data!K337 -> 125.939 | K329: =HAVER_data!L337 -> 125.288 | L329: =HAVER_data!M337 -> 434.93 | ... V329: =HAVER_data!W337 -> 30248.402
A330: 45778 | B330: =HAVER_data!B338 -> 4.375 | C330: =HAVER_data!C338 -> 6.6 | D330: =HAVER_data!D338 -> 4.2 | E330: =HAVER_data!F338 -> 7.8 | F330: =HAVER_data!G338 -> 21942 | G330: =HAVER_data!H338 -> 102875 | H330: =HAVER_data!I338 -> 320.58 | I330: =HAVER_data!J338 -> 326.854 | J330: =HAVER_data!K338 -> 126.11 | K330: =HAVER_data!L338 -> 125.512 | L330: =L329 -> 434.93 | M330: =HAVER_data!N338 -> 128.25 | N330: =HAVER_data!O338 -> 561.29 | O330: =HAVER_data!P338 -> 144 | P330: =HAVER_data!Q338 -> 1049.76 | Q330: =HAVER_data!R338 -> 31.15 | R330: =HAVER_data!S338 -> 4.24 | S330: =HAVER_data!T338 -> 4.11 | T330: =HAVER_data!U338 -> 3.94 | ... V330: =HAVER_data!W338 -> 30064.463
